instrukt_ai_logging/__init__.py
instrukt_ai_logging/cli.py
instrukt_ai_logging/logging.py
instruktai_python_logger-0.1.5.dist-info/METADATA
instruktai_python_logger-0.1.5.dist-info/WHEEL
instruktai_python_logger-0.1.5.dist-info/entry_points.txt
instruktai_python_logger-0.1.5.dist-info/top_level.txt
instruktai_python_logger-0.1.5.dist-info/RECORD
