Metadata-Version: 2.4
Name: instruktai-python-logger
Version: 0.1.5
Summary: Centralized logging utilities for InstruktAI Python services.
Requires-Python: >=3.11
Provides-Extra: dev
Requires-Dist: pytest>=8; extra == "dev"
Requires-Dist: ruff>=0.8; extra == "dev"
